SitanfuCs224nZhongwenBiji2017/README.md
SitanfuCs224nZhongwenBiji2017/__init__.py
SitanfuCs224nZhongwenBiji2017/__main__.py
SitanfuCs224nZhongwenBiji2017/file.epub
SitanfuCs224nZhongwenBiji2017/index.html
SitanfuCs224nZhongwenBiji2017/css/__init__.py
SitanfuCs224nZhongwenBiji2017/css/annotations.css
SitanfuCs224nZhongwenBiji2017/css/main.css
SitanfuCs224nZhongwenBiji2017/css/normalize.css
SitanfuCs224nZhongwenBiji2017/css/popup.css
SitanfuCs224nZhongwenBiji2017/font/__init__.py
SitanfuCs224nZhongwenBiji2017/font/fontello.eot
SitanfuCs224nZhongwenBiji2017/font/fontello.svg
SitanfuCs224nZhongwenBiji2017/font/fontello.ttf
SitanfuCs224nZhongwenBiji2017/font/fontello.woff
SitanfuCs224nZhongwenBiji2017/img/__init__.py
SitanfuCs224nZhongwenBiji2017/img/annotator-glyph-sprite.png
SitanfuCs224nZhongwenBiji2017/img/annotator-icon-sprite.png
SitanfuCs224nZhongwenBiji2017/img/apple-touch-icon.png
SitanfuCs224nZhongwenBiji2017/img/cancelfullscreen.png
SitanfuCs224nZhongwenBiji2017/img/close.png
SitanfuCs224nZhongwenBiji2017/img/fullscreen.png
SitanfuCs224nZhongwenBiji2017/img/loader.gif
SitanfuCs224nZhongwenBiji2017/img/menu-icon.png
SitanfuCs224nZhongwenBiji2017/img/save.png
SitanfuCs224nZhongwenBiji2017/img/saved.png
SitanfuCs224nZhongwenBiji2017/img/settings-s.png
SitanfuCs224nZhongwenBiji2017/img/settings.png
SitanfuCs224nZhongwenBiji2017/img/star.png
SitanfuCs224nZhongwenBiji2017/js/__init__.py
SitanfuCs224nZhongwenBiji2017/js/epub.js
SitanfuCs224nZhongwenBiji2017/js/epub.min.js
SitanfuCs224nZhongwenBiji2017/js/epub.min.map
SitanfuCs224nZhongwenBiji2017/js/hooks.min.js
SitanfuCs224nZhongwenBiji2017/js/hooks.min.map
SitanfuCs224nZhongwenBiji2017/js/reader.js
SitanfuCs224nZhongwenBiji2017/js/reader.js.map
SitanfuCs224nZhongwenBiji2017/js/reader.min.js
SitanfuCs224nZhongwenBiji2017/js/reader.min.map
SitanfuCs224nZhongwenBiji2017/js/hooks/__init__.py
SitanfuCs224nZhongwenBiji2017/js/hooks/extensions/__init__.py
SitanfuCs224nZhongwenBiji2017/js/hooks/extensions/highlight.js
sitanfu_cs224n_zhongwen_biji_2017-2024.3.5.0.dist-info/METADATA
sitanfu_cs224n_zhongwen_biji_2017-2024.3.5.0.dist-info/WHEEL
sitanfu_cs224n_zhongwen_biji_2017-2024.3.5.0.dist-info/entry_points.txt
sitanfu_cs224n_zhongwen_biji_2017-2024.3.5.0.dist-info/top_level.txt
sitanfu_cs224n_zhongwen_biji_2017-2024.3.5.0.dist-info/RECORD
